__init__.py
ai_search_match_framework-0.5.0.dist-info/licenses/LICENSE
asmf/__init__.py
asmf/analyzers/__init__.py
asmf/analyzers/base_analyzer.py
asmf/domain/__init__.py
asmf/domain/config.py
asmf/domain/expert.py
asmf/llm/__init__.py
asmf/llm/model_selector.py
asmf/parsers/__init__.py
asmf/parsers/generic_pdf.py
asmf/parsers/pdf_parser.py
asmf/providers/__init__.py
asmf/providers/base_provider.py
asmf/providers/gemini_provider.py
asmf/providers/ollama_provider.py
asmf/providers/provider_factory.py
asmf/utils/__init__.py
ai_search_match_framework-0.5.0.dist-info/METADATA
ai_search_match_framework-0.5.0.dist-info/WHEEL
ai_search_match_framework-0.5.0.dist-info/top_level.txt
ai_search_match_framework-0.5.0.dist-info/RECORD
