Metadata-Version: 2.4
Name: ai-search-match-framework
Version: 0.5.0
Summary: Lightweight framework for AI-powered document analysis and search workflows with multi-provider support
Author-email: Vincent Caboara <vcaboara@gmail.com>
License-Expression: MIT
Project-URL: Homepage, https://github.com/vcaboara/ai-search-match-framework
Project-URL: Documentation, https://github.com/vcaboara/ai-search-match-framework#readme
Project-URL: Repository, https://github.com/vcaboara/ai-search-match-framework
Project-URL: Issues, https://github.com/vcaboara/ai-search-match-framework/issues
Keywords: ai,llm,analysis,framework,gemini,ollama,document-parsing,patent-analysis
Classifier: Development Status :: 4 - Beta
Classifier: Intended Audience :: Developers
Classifier: Programming Language :: Python :: 3
Classifier: Programming Language :: Python :: 3.10
Classifier: Programming Language :: Python :: 3.11
Classifier: Programming Language :: Python :: 3.12
Classifier: Topic :: Software Development :: Libraries :: Python Modules
Classifier: Topic :: Scientific/Engineering :: Artificial Intelligence
Requires-Python: >=3.10
License-File: LICENSE
Requires-Dist: requests>=2.31.0
Requires-Dist: beautifulsoup4>=4.12.0
Requires-Dist: openai>=1.0.0
Requires-Dist: anthropic>=0.21.0
Requires-Dist: google-generativeai>=0.3.0
Requires-Dist: flask>=3.0.0
Requires-Dist: flask-cors>=4.0.0
Requires-Dist: pypdf>=3.17.0
Requires-Dist: pdfplumber>=0.10.0
Requires-Dist: httpx>=0.25.0
Requires-Dist: playwright>=1.40.0
Requires-Dist: pyyaml>=6.0.0
Provides-Extra: dev
Requires-Dist: pytest>=8.0.0; extra == "dev"
Requires-Dist: pytest-cov>=4.1.0; extra == "dev"
Requires-Dist: pytest-mock>=3.12.0; extra == "dev"
Requires-Dist: pytest-asyncio>=0.23.0; extra == "dev"
Requires-Dist: black>=24.0.0; extra == "dev"
Requires-Dist: isort>=5.13.0; extra == "dev"
Requires-Dist: flake8>=7.0.0; extra == "dev"
Requires-Dist: mypy>=1.8.0; extra == "dev"
Requires-Dist: ruff>=0.1.0; extra == "dev"
Provides-Extra: all
Requires-Dist: ai-search-match-framework[dev]; extra == "all"
Dynamic: license-file
